{
  "project_info": {
    "project_number": "344927788966",
    "firebase_url": "https://nalift-default-rtdb.asia-southeast1.firebasedatabase.app",
    "project_id": "nalift",
    "storage_bucket": "nalift.firebasestorage.app"
  },
  "client": [
    {
      "client_info": {
        "mobilesdk_app_id": "1:344927788966:android:efab7ea05452b982beb967",
        "android_client_info": {
          "package_name": "com.kevin.nalift"
        }
      },
      "oauth_client": [],
      "api_key": [
        {
          "current_key": "AIzaSyANJYcuWXt_1IAp7pYkeYdzjpYeQ9AKYT0"
        }
      ],
      "services": {
        "appinvite_service": {
          "other_platform_oauth_client": []
        }
      }
    }
  ],
  "configuration_version": "1"
}